setup.py
django_emailqueue/__init__.py
django_emailqueue/admin.py
django_emailqueue/cron.py
django_emailqueue/models.py
django_emailqueue/tests.py
django_emailqueue.egg-info/PKG-INFO
django_emailqueue.egg-info/SOURCES.txt
django_emailqueue.egg-info/dependency_links.txt
django_emailqueue.egg-info/entry_points.txt
django_emailqueue.egg-info/top_level.txt