Metadata-Version: 1.1
Name: django-emailqueue
Version: 0.2
Summary: Django app for sending queued emails using cron
Home-page: http://github.com/humanfromearth/django-emailqueue
Author: Alexandru Plugaru
Author-email: alexandru.plugaru@gmail.com
License: GPLv3
Platform: UNKNOWN
Classifier: Development Status :: 2 - Pre-Alpha
Classifier: Environment :: Web Environment
Classifier: Framework :: Django
Classifier: Intended Audience :: Developers
Classifier: License :: OSI Approved :: GNU General Public License (GPL)
Classifier: Operating System :: OS Independent
Classifier: Programming Language :: Python
Classifier: Topic :: Software Development
Requires: django (>=1.0)
